Metadata-Version: 1.1
Name: proatac
Version: 0.4.0
Summary: Processing and quality control of ATAC data.
Home-page: https://github.com/buenrostrolab/proatac
Author: Caleb Lareau
Author-email: caleblareau@g.harvard.edu
License: MIT
Platform: any
Classifier: Development Status :: 4 - Beta
Classifier: Environment :: Console
Classifier: Intended Audience :: Developers
Classifier: License :: OSI Approved :: MIT License
Classifier: Operating System :: POSIX
Classifier: Operating System :: MacOS
Classifier: Operating System :: Unix
Classifier: Programming Language :: Python
Classifier: Programming Language :: Python :: 3
Classifier: Topic :: Software Development :: Libraries :: Python Modules
